netlink/sharepoint/alchemy/__init__.py
netlink/sharepoint/alchemy/_base.py
netlink_sharepoint_alchemy-0.0.6.dist-info/WHEEL
netlink_sharepoint_alchemy-0.0.6.dist-info/METADATA
netlink_sharepoint_alchemy-0.0.6.dist-info/RECORD
