Metadata-Version: 2.1
Name: netlink-sharepoint-alchemy
Version: 0.0.6
Summary: Integrate Sharepoint and SQL Alchemy
Home-page: https://gitlab.com/netlink_python/netlink-sharepoint-alchemy
License: MIT
Keywords: sharepoint
Author: Bernhard Radermacher
Author-email: bernhard.radermacher@netlink-consulting.com
Requires-Python: >=3.8,<=3.12
Classifier: License :: OSI Approved :: MIT License
Classifier: Programming Language :: Python :: 3
Classifier: Programming Language :: Python :: 3.10
Classifier: Programming Language :: Python :: 3.8
Classifier: Programming Language :: Python :: 3.9
Classifier: Topic :: Software Development
Requires-Dist: netlink-alchemy (>=0.0.1)
Requires-Dist: netlink-sharepoint-base (>=0.0.6)
Project-URL: Repository, https://gitlab.com/netlink_python/netlink-sharepoint-alchemy
